[
  {
    "listing": "/posts/posts.html",
    "items": [
      "/posts/nextflow-tutorial/index.html",
      "/posts/post-with-code/index.html",
      "/posts/welcome/index.html"
    ]
  },
  {
    "listing": "/projects/projects.html",
    "items": [
      "/projects/TEKRABber/index.html"
    ]
  },
  {
    "listing": "/index.html",
    "items": [
      "/posts/nextflow-tutorial/index.html",
      "/posts/post-with-code/index.html",
      "/posts/welcome/index.html",
      "/projects/TEKRABber/index.html"
    ]
  }
]